design.sv
module gray2bin (
  input [3:0] gray,
  output [3:0] bin);

  wire not_gray3, not_gray2, not_gray1, not_gray0;
  
  wire aux_b21, aux_b22;
  wire aux_b31, aux_b32, aux_b33, aux_b34;
  wire aux_b41, aux_b42, aux_b43, aux_b44, aux_b45, aux_b46, aux_b47, aux_b48;
  
  not gray3_inv (not_gray3, gray[3]);
  not gray2_inv (not_gray2, gray[2]);
  not gray1_inv (not_gray1, gray[1]);
  not gray0_inv (not_gray0, gray[0]);

  and aux_b21(aux_b21, gray[3],not_gray2);
  and aux_b22(aux_b22, not_gray3, gray[2]);

  and aux_b31(aux_b31, gray[1], not_gray2, not_gray3);
  and aux_b32(aux_b32, gray[2], not_gray1, not_gray3);
  and aux_b33(aux_b33, gray[1], gray[2], gray[3]);
  and aux_b34(aux_b34, gray[3], not_gray1, not_gray2);

  and aux_b41(aux_b41, gray[0], not_gray1, not_gray2, not_gray3);
  and aux_b42(aux_b42, gray[1], not_gray0, not_gray2, not_gray3);
  and aux_b43(aux_b43, gray[2], not_gray0, not_gray1, not_gray3);
  and aux_b44(aux_b44, gray[1], gray[2], gray[3], not_gray0);
  and aux_b45(aux_b45, gray[1], gray[0], gray[3], not_gray2);
  and aux_b46(aux_b46, gray[2], gray[3], gray[1], not_gray0);
  and aux_b47(aux_b47, gray[3], not_gray1, not_gray2, not_gray0);
  and aux_b48(aux_b48, not_gray2, gray[0], gray[1], gray[3]);

  buf(bin[3], gray[3]);
  or b2(bin[2], aux_b21,aux_b22);
  or b1(bin[1], aux_b31, aux_b32, aux_b33, aux_b34);
  or b0(bin[0], aux_b41, aux_b42, aux_b43, aux_b44, aux_b45, aux_b46, aux_b47, aux_b48);

  initial begin
    $monitor("%b <-> %b", gray, bin);
  end
endmodule

testbench.sv
module gray2bin_testbench;
  reg[3:0] gray_in;

  wire[3:0] bin_out;

  gray2bin uut(gray_in, bin_out);

  initial
 	begin
      $dumpfile("dump.vcd"); $dumpvars;
      $display("gray <-> bin");

      gray_in = 4'b0000; #1;
      gray_in = 4'b0001; #1;
      gray_in = 4'b0011; #1;
      gray_in = 4'b0010; #1;
      gray_in = 4'b0110; #1;
      gray_in = 4'b0111; #1;
      gray_in = 4'b0101; #1;
      gray_in = 4'b0100; #1;
      gray_in = 4'b1100; #1;
      gray_in = 4'b1101; #1;
      gray_in = 4'b1111; #1;
      gray_in = 4'b1110; #1;
      gray_in = 4'b1010; #1;
      gray_in = 4'b1011; #1;
      gray_in = 4'b1001; #1;
      gray_in = 4'b1000; #1;
    end
endmodule

dump.vcd
$date
	Thu Oct 20 08:44:37 2022
$end
$version
	Icarus Verilog
$end
$timescale
	1s
$end
$scope module gray2bin_testbench $end
$var wire 4 ! bin_out [3:0] $end
$var reg 4 " gray_in [3:0] $end
$scope module uut $end
$var wire 1 # aux_b21 $end
$var wire 1 $ aux_b22 $end
$var wire 1 % aux_b31 $end
$var wire 1 & aux_b32 $end
$var wire 1 ' aux_b33 $end
$var wire 1 ( aux_b34 $end
$var wire 1 ) aux_b41 $end
$var wire 1 * aux_b42 $end
$var wire 1 + aux_b43 $end
$var wire 1 , aux_b44 $end
$var wire 1 - aux_b45 $end
$var wire 1 . aux_b46 $end
$var wire 1 / aux_b47 $end
$var wire 1 0 aux_b48 $end
$var wire 4 1 gray [3:0] $end
$var wire 1 2 not_gray0 $end
$var wire 1 3 not_gray1 $end
$var wire 1 4 not_gray2 $end
$var wire 1 5 not_gray3 $end
$var wire 4 6 bin [3:0] $end
$upscope $end
$upscope $end
$enddefinitions $end
#0
$dumpvars
b0 6
15
14
13
12
b0 1
00
0/
0.
0-
0,
0+
0*
0)
0(
0'
0&
0%
0$
0#
b0 "
b0 !
$end
#1
b1 !
b1 6
02
1)
b1 "
b1 1
#2
0)
b10 !
b10 6
03
1%
b11 "
b11 1
#3
b11 !
b11 6
1*
12
b10 "
b10 1
#4
0%
0*
b100 !
b100 6
04
1$
b110 "
b110 1
#5
02
b111 "
b111 1
#6
b110 !
b110 6
1&
13
b101 "
b101 1
#7
b111 !
b111 6
1+
12
b100 "
b100 1
#8
0$
0&
0+
05
b1000 !
b1000 6
b1100 "
b1100 1
#9
02
b1101 "
b1101 1
#10
b1010 !
b1010 6
03
1'
b1111 "
b1111 1
#11
b1011 !
b1011 6
1,
1.
12
b1110 "
b1110 1
#12
1#
b1100 !
b1100 6
14
0'
0,
0.
b1010 "
b1010 1
#13
b1101 !
b1101 6
02
1-
10
b1011 "
b1011 1
#14
b1110 !
b1110 6
1(
13
0-
00
b1001 "
b1001 1
#15
b1111 !
b1111 6
1/
12
b1000 "
b1000 1
